BigStash/api.py
BigStash/auth.py
BigStash/base.py
BigStash/conf.py
BigStash/decorators.py
BigStash/error.py
BigStash/filename.py
BigStash/manifest.py
BigStash/models.py
BigStash/serialize.py
BigStash/sign.py
BigStash/structures.py
BigStash/upload.py
BigStash/uploader.py
BigStash/version.py
BigStash/winargvfix.py
BigStash/wtf8.py
BigStash/__init__.py
bigstash-1.3.dist-info/DESCRIPTION.rst
bigstash-1.3.dist-info/entry_points.txt
bigstash-1.3.dist-info/METADATA
bigstash-1.3.dist-info/metadata.json
bigstash-1.3.dist-info/RECORD
bigstash-1.3.dist-info/top_level.txt
bigstash-1.3.dist-info/WHEEL
