Metadata-Version: 2.0
Name: bigstash
Version: 1.3
Summary: The BigStash Python SDK
Requires-Dist: six (>=1.9,<2.0)
Requires-Dist: requests (>=2.5.1,<2.6)
Requires-Dist: retrying
Requires-Dist: wrapt
Requires-Dist: boto3
Requires-Dist: cached-property
Requires-Dist: docopt
Requires-Dist: inflect
Requires-Dist: futures; python_version=="2.6" or python_version=="2.7"
Provides-Extra: dev
Requires-Dist: flake8; extra == 'dev'
